CHANGELOG.md
LICENSE
README.md
mdut/__init__.py
mdut/mdut.py
mdut-22.6.0.dist-info/entry_points.txt
mdut-22.6.0.dist-info/LICENSE
mdut-22.6.0.dist-info/WHEEL
mdut-22.6.0.dist-info/METADATA
mdut-22.6.0.dist-info/RECORD
