Metadata-Version: 2.1
Name: mdut
Version: 22.6.0
Summary: Markdown URL tag generator
Home-page: https://github.com/nkantar/mdut
License: MIT
Keywords: markdown
Author: Nik Kantar
Author-email: nik@nkantar.com
Requires-Python: >=3.7,<4.0
Classifier: Development Status :: 5 - Production/Stable
Classifier: Environment :: Console
Classifier: Intended Audience :: Developers
Classifier: License :: OSI Approved :: MIT License
Classifier: Programming Language :: Python :: 3
Classifier: Programming Language :: Python :: 3.10
Classifier: Programming Language :: Python :: 3.11
Classifier: Programming Language :: Python :: 3.7
Classifier: Programming Language :: Python :: 3.8
Classifier: Programming Language :: Python :: 3.9
Classifier: Topic :: Internet :: WWW/HTTP
Classifier: Topic :: Software Development :: Code Generators
Classifier: Topic :: Software Development :: Libraries
Classifier: Topic :: Text Processing :: Markup :: Markdown
Classifier: Topic :: Utilities
Classifier: Typing :: Typed
Requires-Dist: beautifulsoup4 (>=4.11.1,<5.0.0)
Requires-Dist: click (>=8.1.3,<9.0.0)
Requires-Dist: httpx (>=0.23.0,<0.24.0)
Requires-Dist: pyperclip (>=1.8.2,<2.0.0)
Project-URL: Documentation, https://github.com/nkantar/mdut
Project-URL: Repository, https://github.com/nkantar/mdut
